Metadata-Version: 2.1
Name: urlshortening
Version: 1.0.0
Summary: A URL shortening app for Django.
Home-page: https://github.com/Enkompass/django-urlshortening
Author: Enkompass
Author-email: jvazquez@enkompass.net
License: BSD
Classifier: Development Status :: 5 - Production/Stable
Classifier: Framework :: Django
Classifier: Intended Audience :: Developers
Classifier: License :: OSI Approved :: BSD License
Classifier: Operating System :: OS Independent
Classifier: Programming Language :: Python :: 3.8
Classifier: Topic :: Internet :: WWW/HTTP
License-File: LICENSE
Requires-Dist: setuptools
Requires-Dist: six
Requires-Dist: Django<6.0,>=3.2
